bmsdna/__init__.py
bmsdna/sql_utils/__init__.py
bmsdna/sql_utils/async_db_helper.py
bmsdna/sql_utils/case_preserving_set.py
bmsdna/sql_utils/db_helper.py
bmsdna/sql_utils/dbapi.py
bmsdna/sql_utils/integrity_check.py
bmsdna/sql_utils/query.py
bmsdna/sql_utils/query_generation.py
bmsdna/sql_utils/result.py
bmsdna/sql_utils/server_info.py
bmsdna/sql_utils/sql_gen.py
bmsdna/sql_utils/db_io/__init__.py
bmsdna/sql_utils/db_io/arrow_utils.py
bmsdna/sql_utils/db_io/db_logging.py
bmsdna/sql_utils/db_io/delta_polars_source.py
bmsdna/sql_utils/db_io/delta_source.py
bmsdna/sql_utils/db_io/fill_table.py
bmsdna/sql_utils/db_io/json_insert.py
bmsdna/sql_utils/db_io/lake_source.py
bmsdna/sql_utils/db_io/meta_sql_store.py
bmsdna/sql_utils/db_io/source.py
bmsdna/sql_utils/db_io/source_spark.py
bmsdna/sql_utils/db_io/sql_utils.py
bmsdna/sql_utils/db_io/sqlschema.py
bmsdna/sql_utils/lake/__init__.py
bmsdna/sql_utils/lake/lake_meta.py
bmsdna/sql_utils/lake/type_fromarrow.py
bmsdna/sql_utils/lake/types.py
bmsdna/sql_utils/metadata/__init__.py
bmsdna_sql_utils-0.14.7.dist-info/METADATA
bmsdna_sql_utils-0.14.7.dist-info/WHEEL
bmsdna_sql_utils-0.14.7.dist-info/RECORD
