Metadata-Version: 2.4
Name: bmsdna-sql-utils
Version: 0.14.7
Author-email: Adrian Ehrsam <adrian.ehrsam@bmsuisse.ch>
Requires-Python: ~=3.11
Provides-Extra: db-io
Requires-Dist: aioodbc>=0.5.0; extra == 'db-io'
Requires-Dist: lakeapi2sql; extra == 'db-io'
Requires-Dist: pyodbc; extra == 'db-io'
Provides-Extra: db2delta
Requires-Dist: aiohttp; extra == 'db2delta'
Requires-Dist: arrow-odbc; extra == 'db2delta'
Requires-Dist: deltalake2db; extra == 'db2delta'
Requires-Dist: deltalake>=0.16.4; extra == 'db2delta'
Requires-Dist: duckdb>=1.2; extra == 'db2delta'
Provides-Extra: delta
Requires-Dist: deltalake2db<1.0.0; extra == 'delta'
Requires-Dist: deltalake>=0.16.4; extra == 'delta'
Requires-Dist: duckdb; extra == 'delta'
Provides-Extra: lake-api
Requires-Dist: aiohttp<4,>=3.8.5; extra == 'lake-api'
Requires-Dist: requests>=2.28.0; extra == 'lake-api'
Provides-Extra: mssql
Requires-Dist: mssql-python>=0.13.1; extra == 'mssql'
Provides-Extra: odbc
Requires-Dist: aioodbc>=0.5.0; extra == 'odbc'
Requires-Dist: lakeapi2sql>=0.9.1; extra == 'odbc'
Requires-Dist: pyodbc<6,>=5.0.1; extra == 'odbc'
Provides-Extra: polars
Requires-Dist: polars>=1.0.0; extra == 'polars'
